pysparkme/__init__.py
pysparkme/functions.py
pysparkme/databricks/__init__.py
pysparkme/databricks/common.py
pysparkme/databricks/connection.py
pysparkme/databricks/databricks_data_classes.py
pysparkme/databricks/dbfs.py
pysparkme/databricks/jobs.py
pysparkme/databricks/legacy.py
pysparkme/databricks/runs.py
pysparkme/databricks/workspace.py
pysparkme/databricks/cli/__init__.py
pysparkme/databricks/cli/__main__.py
pysparkme/databricks/cli/cli.py
tests/__init__.py
tests/conftest.py
tests/test_functions.py
pyspark_me-0.0.6.dist-info/LICENSE
pyspark_me-0.0.6.dist-info/METADATA
pyspark_me-0.0.6.dist-info/WHEEL
pyspark_me-0.0.6.dist-info/entry_points.txt
pyspark_me-0.0.6.dist-info/top_level.txt
pyspark_me-0.0.6.dist-info/RECORD
